lisk_name_service/__init__.py
lisk_name_service/client.py
lisk_name_service-1.0.0.dist-info/METADATA
lisk_name_service-1.0.0.dist-info/WHEEL
lisk_name_service-1.0.0.dist-info/top_level.txt
lisk_name_service-1.0.0.dist-info/RECORD
