Metadata-Version: 2.4
Name: lisk-name-service
Version: 1.0.0
Summary: Python SDK for resolving Lisk Name Service (.lisk) names
Author: Wiseman Umanah
Author-email: Wiseman Umanah <wisemanumanah@gmail.com>, Emmanuel Bassey <basscee1604@gmail.com>
License-Expression: MIT
Requires-Python: >=3.7
Requires-Dist: requests
